CHANGES.rst
CONTRIBUTORS.rst
MANIFEST.in
README.rst
VERSION
setup.py
docs/LICENSE.GPL
docs/LICENSE.rst
docs/index.rst
src/visaplan/__init__.py
src/visaplan.plone.sqlwrapper.egg-info/PKG-INFO
src/visaplan.plone.sqlwrapper.egg-info/SOURCES.txt
src/visaplan.plone.sqlwrapper.egg-info/dependency_links.txt
src/visaplan.plone.sqlwrapper.egg-info/entry_points.txt
src/visaplan.plone.sqlwrapper.egg-info/namespace_packages.txt
src/visaplan.plone.sqlwrapper.egg-info/not-zip-safe
src/visaplan.plone.sqlwrapper.egg-info/requires.txt
src/visaplan.plone.sqlwrapper.egg-info/top_level.txt
src/visaplan/plone/__init__.py
src/visaplan/plone/sqlwrapper/__init__.py
src/visaplan/plone/sqlwrapper/adapter.py
src/visaplan/plone/sqlwrapper/configure.zcml
src/visaplan/plone/sqlwrapper/qfactory.py
src/visaplan/plone/sqlwrapper/utils.py